ipsae/__init__.py
ipsae/cli.py
ipsae/core.py
ipsae-1.0.1.dist-info/licenses/LICENSE
ipsae-1.0.1.dist-info/METADATA
ipsae-1.0.1.dist-info/WHEEL
ipsae-1.0.1.dist-info/entry_points.txt
ipsae-1.0.1.dist-info/top_level.txt
ipsae-1.0.1.dist-info/RECORD
