Metadata-Version: 2.4
Name: ipsae
Version: 1.0.1
Summary: Calculate ipSAE scores for protein-protein interactions in AlphaFold2 and AlphaFold3 models
Author-email: SameeUllah <sameeullah@bs.qau.edu.pk>
License: MIT
Project-URL: Homepage, https://github.com/ullahsamee/IPSAE
Project-URL: Repository, https://github.com/ullahsamee/IPSAE
Project-URL: Issues, https://github.com/ullahsamee/IPSAE
Keywords: protein,alphafold,bioinformatics,structural-biology
Classifier: Development Status :: 4 - Beta
Classifier: Intended Audience :: Science/Research
Classifier: Topic :: Scientific/Engineering :: Bio-Informatics
Classifier: License :: OSI Approved :: MIT License
Classifier: Programming Language :: Python :: 3
Classifier: Programming Language :: Python :: 3.7
Classifier: Programming Language :: Python :: 3.8
Classifier: Programming Language :: Python :: 3.9
Classifier: Programming Language :: Python :: 3.10
Classifier: Programming Language :: Python :: 3.11
Requires-Python: >=3.7
License-File: LICENSE
Requires-Dist: numpy>=1.19.0
Provides-Extra: dev
Requires-Dist: pytest>=6.0; extra == "dev"
Requires-Dist: pytest-cov; extra == "dev"
Requires-Dist: black; extra == "dev"
Requires-Dist: flake8; extra == "dev"
Dynamic: license-file
